info/__Constants__.py
info/__Core__.py
info/__init__.py
info/__main__.py
infopkg-3.2.1.dist-info/LICENSE
infopkg-3.2.1.dist-info/METADATA
infopkg-3.2.1.dist-info/WHEEL
infopkg-3.2.1.dist-info/top_level.txt
infopkg-3.2.1.dist-info/RECORD
