Metadata-Version: 2.1
Name: infopkg
Version: 3.2.1
Summary: Do you want information about your packages?
Home-page: https://github.com/ArticOff/info
Author: Artic#3065
Author-email: artic.admisoffi@gmail.com
Maintainer: Artic#3065
Maintainer-email: artic.admisoffi@gmail.com
License: MIT
Project-URL: Source, https://github.com/ArticOff/info
Project-URL: Discord, https://articoff.github.io/discord
Project-URL: Tracker, https://github.com/ArticOff/info/issues
Platform: UNKNOWN
Classifier: Development Status :: 5 - Production/Stable
Classifier: License :: OSI Approved :: MIT License
Classifier: Intended Audience :: Developers
Classifier: Natural Language :: English
Classifier: Programming Language :: Python :: 3
Classifier: Programming Language :: Python
Classifier: Environment :: Console
Classifier: Environment :: Win32 (MS Windows)
Classifier: Framework :: Pytest
Classifier: Operating System :: OS Independent
Classifier: Topic :: Internet
License-File: LICENSE
